tokopedia/__init__.py
tokopedia/access_token.py
tokopedia/base.py
tokopedia/campaign/__init__.py
tokopedia/category/__init__.py
tokopedia/chat/__init__.py
tokopedia/constants.py
tokopedia/finance/__init__.py
tokopedia/logistic/__init__.py
tokopedia/order/__init__.py
tokopedia/order/api.py
tokopedia/product/__init__.py
tokopedia/product/active_products.py
tokopedia/product/api/__init__.py
tokopedia/product/api/create_product.py
tokopedia/product/api/get_product.py
tokopedia/product/api/get_product_variant.py
tokopedia/product/api/product_api.py
tokopedia/product/create_product_v3.py
tokopedia/product/product.py
tokopedia/product/product_v2.py
tokopedia/product/variant_category.py
tokopedia/product/variant_product.py
tokopedia/response.py
tokopedia/shop/__init__.py
tokopedia/shop/api.py
tokopedia/statistic/__init__.py
tokopedia/tokopedia.py
tokopedia/utils.py
tokopedia/version.py
tokopedia/webhook/__init__.py
tokopedia-0.4.2.dist-info/LICENSE
tokopedia-0.4.2.dist-info/WHEEL
tokopedia-0.4.2.dist-info/METADATA
tokopedia-0.4.2.dist-info/RECORD
