Metadata-Version: 2.1
Name: tokopedia
Version: 0.4.2
Summary: Python SDK for Tokopedia Seller API 
Keywords: tokopedia,openapi,api-client,tokopedia-api,seller-api
Author: hexatester
Author-email: hexatester@protonmail.com
Requires-Python: >=3.7,<4.0
Classifier: Development Status :: 3 - Alpha
Classifier: Intended Audience :: Developers
Classifier: License :: OSI Approved :: MIT License
Classifier: Operating System :: OS Independent
Classifier: Programming Language :: Python :: 3
Classifier: Programming Language :: Python :: 3.10
Classifier: Programming Language :: Python :: 3.7
Classifier: Programming Language :: Python :: 3.8
Classifier: Programming Language :: Python :: 3.9
Classifier: Topic :: Office/Business
Requires-Dist: attrs (>=20.3.0,<21.0.0)
Requires-Dist: cattrs (>=1.3.0,<2.0.0)
Requires-Dist: python-dateutil (>=2.8.1,<3.0.0)
Requires-Dist: requests (>=2.25.1,<3.0.0)
